mtdata/__init__.py
mtdata/__main__.py
mtdata/cache.py
mtdata/data.py
mtdata/entry.py
mtdata/main.py
mtdata/map.py
mtdata/opus_xces.py
mtdata/parser.py
mtdata/pigz.py
mtdata/scorer.py
mtdata/sgm.py
mtdata/tmx.py
mtdata/utils.py
mtdata/index/__init__.py
mtdata/index/ai4bharat.py
mtdata/index/allenai_nllb.py
mtdata/index/anuvaad.py
mtdata/index/elrc_share.py
mtdata/index/eu.py
mtdata/index/flores.py
mtdata/index/huggingface.py
mtdata/index/joshua_indian.py
mtdata/index/leipzig.py
mtdata/index/linguatools.py
mtdata/index/neulab_tedtalks.py
mtdata/index/other.py
mtdata/index/paracrawl.py
mtdata/index/statmt.py
mtdata/index/tilde.py
mtdata/index/unitednations.py
mtdata/index/wikimatrix.py
mtdata/index/opus/__init__.py
mtdata/index/opus/crawl_parse.py
mtdata/index/opus/jw300.py
mtdata/index/opus/opus100.py
mtdata/index/opus/opus_index.py
mtdata/iso/__init__.py
mtdata/iso/__main__.py
mtdata/iso/bcp47.json
mtdata/iso/bcp47.py
mtdata/iso/custom.py
mtdata/iso/iso639.py
mtdata/iso/iso639_1.py
mtdata/iso/iso639_2.py
mtdata/iso/iso639_3.py
mtdata/recipe/__init__.py
mtdata/resource/allenai_nllb.json
mtdata/resource/anuvaad.tsv
mtdata/resource/elrc_share.tsv
mtdata/resource/huggingface-datasets.all.jsonl
mtdata/resource/huggingface-datasets.jsonl
mtdata/resource/leipzig_de.txt
mtdata/resource/opus_index.tsv
mtdata/resource/recipes.yml
mtdata/resource/refs.bib
mtdata/scripts/recipe_stats.py
mtdata/scripts/tsv2xls.py
mtdata-0.4.3.dist-info/METADATA
mtdata-0.4.3.dist-info/WHEEL
mtdata-0.4.3.dist-info/entry_points.txt
mtdata-0.4.3.dist-info/top_level.txt
mtdata-0.4.3.dist-info/RECORD
