Metadata-Version: 2.4
Name: mtdata
Version: 0.4.3
Summary: mtdata is a tool to download datasets for machine translation
Author-email: Thamme Gowda <tgowdan@gmail.com>
Project-URL: homepage, https://github.com/thammegowda/mtdata
Project-URL: documentation, https://github.com/thammegowda/mtdata
Project-URL: repository, https://github.com/thammegowda/mtdata
Keywords: machine translation,datasets,NLP,natural language processing,computational linguistics
Classifier: Development Status :: 5 - Production/Stable
Classifier: Intended Audience :: Developers
Classifier: Topic :: Utilities
Classifier: Topic :: Text Processing
Classifier: Topic :: Text Processing :: General
Classifier: Topic :: Text Processing :: Filters
Classifier: Topic :: Text Processing :: Linguistic
Classifier: Programming Language :: Python :: 3 :: Only
Requires-Python: >=3.9
Requires-Dist: requests>=2.32.0
Requires-Dist: enlighten==1.10.1
Requires-Dist: portalocker==2.3.0
Requires-Dist: pybtex==0.24.0
Requires-Dist: ruamel.yaml>=0.17.10
Provides-Extra: hf
Requires-Dist: datasets>=3.1.0; extra == "hf"
Provides-Extra: test
Requires-Dist: pytest; extra == "test"
Requires-Dist: pytest-cov[all]; extra == "test"
Requires-Dist: black; extra == "test"
Requires-Dist: isort; extra == "test"
Requires-Dist: mypy; extra == "test"
